school_management/__init__.py
school_management/course.py
school_management/student.py
school_management-0.1.dist-info/METADATA
school_management-0.1.dist-info/WHEEL
school_management-0.1.dist-info/top_level.txt
school_management-0.1.dist-info/RECORD
