Metadata-Version: 2.1
Name: school-management
Version: 0.1
Summary: A package for managing school courses and students
Home-page: UNKNOWN
Author: hanyong
License: UNKNOWN
Platform: UNKNOWN
Requires-Python: >=3.6
